pyibc_api/__init__.py
pyibc_api/chain_apis.py
pyibc_chain/__init__.py
pyibc_chain/queries.py
pyibc_chain/tx_queries.py
pyibc_chain/validators.py
pyibc_price/__init__.py
pyibc_price/token_price.py
pyibc_utils/__init__.py
pyibc_utils/convert.py
python_ibc-0.2.0.dist-info/LICENSE
python_ibc-0.2.0.dist-info/METADATA
python_ibc-0.2.0.dist-info/WHEEL
python_ibc-0.2.0.dist-info/top_level.txt
python_ibc-0.2.0.dist-info/RECORD
