Metadata-Version: 2.1
Name: python-ibc
Version: 0.2.0
Summary: A library to make developing python based programs on cosmos chains easier
Home-page: https://github.com/Reecepbcups/pyibc
Author: Reece Williams
Author-email: reecepbcups@gmail.com
Keywords: Cosmos Blockchain,Cosmoshub,atom token
Classifier: Development Status :: 4 - Beta
Classifier: Programming Language :: Python :: 3
Classifier: Programming Language :: Python :: 3.6
Classifier: Programming Language :: Python :: 3.7
Classifier: Programming Language :: Python :: 3.8
Classifier: Programming Language :: Python :: 3.9
Classifier: License :: OSI Approved :: BSD License
Classifier: Intended Audience :: Developers
Classifier: Intended Audience :: Other Audience
Classifier: Intended Audience :: Science/Research
Classifier: Intended Audience :: Education
Classifier: Topic :: Text Processing
Classifier: Operating System :: Microsoft :: Windows
Classifier: Operating System :: OS Independent
License-File: LICENSE
Requires-Dist: requests (>=2.20.0)
